jumper_logging_agent
