Metadata-Version: 1.1
Name: jumper-logging-agent
Version: 0.1.0
Summary: The jumper background logging agent for Linux and Windows systems
Home-page: https://github.com/jumperr-labs/jumper-logging-agent
Author: Roy Razon
Author-email: roy@jumper.io
License: Apache 2.0
Download-URL: https://github.com/Jumperr-labs/jumper-logging-agent/archive/0.1.0.tar.gz
Keywords: logging iot
Platform: UNKNOWN
Classifier: Development Status :: 3 - Alpha
Classifier: Intended Audience :: Developers
Classifier: Intended Audience :: System Administrators
Classifier: Topic :: System :: Logging
Classifier: License :: OSI Approved :: MIT License
Classifier: Programming Language :: Python :: 2
Classifier: Programming Language :: Python :: 2.7
Classifier: Programming Language :: Python :: 3
Classifier: Programming Language :: Python :: 3.3
Classifier: Programming Language :: Python :: 3.4
Classifier: Programming Language :: Python :: 3.5
Classifier: Programming Language :: Python :: 3.6
